indoxhub/__init__.py
indoxhub/client.py
indoxhub/constants.py
indoxhub/exceptions.py
indoxhub-0.1.43.dist-info/licenses/LICENSE
indoxhub-0.1.43.dist-info/METADATA
indoxhub-0.1.43.dist-info/WHEEL
indoxhub-0.1.43.dist-info/top_level.txt
indoxhub-0.1.43.dist-info/RECORD
