Metadata-Version: 2.4
Name: indoxhub
Version: 0.1.43
Summary: A unified client for various AI providers
Author-email: indoxHub Team <ashkan.eskandari.dev@gmail.com>
License: MIT
Project-URL: Homepage, https://github.com/osllmai/indoxHub
Project-URL: Repository, https://github.com/osllmai/indoxHub
Project-URL: Issues, https://github.com/osllmai/indoxHub/issues
Keywords: ai,api,client,openai,anthropic,google,mistral,xai,imagen,grok,image-generation,text-to-speech,tts,audio
Classifier: Development Status :: 3 - Alpha
Classifier: Intended Audience :: Developers
Classifier: Programming Language :: Python :: 3
Classifier: Programming Language :: Python :: 3.8
Classifier: Programming Language :: Python :: 3.9
Classifier: Programming Language :: Python :: 3.10
Classifier: Programming Language :: Python :: 3.11
Classifier: Programming Language :: Python :: 3.12
Requires-Python: >=3.8
License-File: LICENSE
Requires-Dist: requests>=2.25.0
Requires-Dist: python-dotenv>=1.0.0
Dynamic: license-file
